django_ratelimit_middleware/__init__.py
django_ratelimit_middleware/middleware.py
django_ratelimit_middleware-0.1.1.dist-info/METADATA
django_ratelimit_middleware-0.1.1.dist-info/WHEEL
django_ratelimit_middleware-0.1.1.dist-info/licenses/LICENSE
django_ratelimit_middleware-0.1.1.dist-info/RECORD
