Metadata-Version: 2.4
Name: django-ratelimit-middleware
Version: 0.1.1
Summary: A simple Django middleware for rate limiting by IP or user
Project-URL: Homepage, https://github.com/k3y5tr0k3/django-ratelimit-middleware
Author-email: Bryan Donnelly <bryandonnelly7@gmail.com>
License-File: LICENSE
Classifier: Framework :: Django
Classifier: License :: OSI Approved :: MIT License
Classifier: Programming Language :: Python :: 3
Classifier: Programming Language :: Python :: 3.12
Requires-Python: >=3.12
Requires-Dist: django>=5.1
